[
  {
    "id": "eei",
    "name": "EEI 商域图谱",
    "category": "Enterprise Ecosystem Intelligence",
    "compatibilityLevel": "L2",
    "deploymentStatus": "Live",
    "futureLevel": "L3 gated",
    "summary": "美国商业权力地图：以公司为中心的关系图谱与递归供应链探索，Owner 签核事实全链路可溯源；云端 7×24 运行。",
    "liveUrl": "https://eei.linzezhang.com",
    "fallbackUrl": "https://github.com/LinzeColin/MetaDatabase/tree/main/EEI",
    "mode": "voyage"
  },
  {
    "id": "memory-atlas",
    "name": "OpenAIDatabase / MemoryAtlas",
    "category": "Redacted Memory Viewer",
    "compatibilityLevel": "L2",
    "deploymentStatus": "Protected",
    "futureLevel": "L3 gated",
    "summary": "脱敏派生快照的只读记忆可视化；custom、production Pages 与 preview Pages 均由 owner allowlist Access 保护并完成授权加载验证。",
    "liveUrl": "https://memoryatlas.linzezhang.com",
    "fallbackUrl": "https://github.com/LinzeColin/CodexProject/tree/main/OpenAIDatabase/apps/memory-atlas",
    "mode": "archive"
  },
  {
    "id": "pfi",
    "name": "PFI",
    "category": "Financial Intelligence Shell",
    "compatibilityLevel": "L2",
    "deploymentStatus": "Live",
    "futureLevel": "L3 gated",
    "summary": "不读取账户、组合、交易或本地数据库的公开产品壳，只展示脱敏后的能力结构。",
    "liveUrl": "https://codex-pfi.linzezhang35.workers.dev",
    "fallbackUrl": "https://github.com/LinzeColin/CodexProject/tree/main/PFI/web/cloudflare-public",
    "mode": "garden"
  },
  {
    "id": "serenity-alipay",
    "name": "Serenity-Alipay",
    "category": "Human Review Cockpit",
    "compatibilityLevel": "L2",
    "deploymentStatus": "Live",
    "futureLevel": "L3 gated",
    "summary": "只读、脱敏、人工确认优先的公开驾驶舱；不会读取账户、发送邮件、通知或移动资金。",
    "liveUrl": "https://serenity-alipay.linzezhang35.workers.dev",
    "fallbackUrl": "https://github.com/LinzeColin/CodexProject/tree/main/Serenity-Alipay/app/cloudflare-public",
    "mode": "voyage"
  },
  {
    "id": "nab",
    "name": "NAB IR Roadshow",
    "category": "Archive Experiment",
    "compatibilityLevel": "L2",
    "deploymentStatus": "Live",
    "futureLevel": "L3 gated",
    "summary": "已验证可访问的归档型投资者关系路演实验；Cloudflare 源已迁入 Archive/nab。",
    "liveUrl": "https://nab.linzezhang.com",
    "fallbackUrl": "https://github.com/LinzeColin/Archive/tree/main/nab",
    "mode": "archive"
  },
  {
    "id": "account",
    "name": "Account / 统一登录",
    "category": "Identity & SSO",
    "compatibilityLevel": "L2",
    "deploymentStatus": "Live",
    "futureLevel": "L3 gated",
    "summary": "linzezhang.com 统一身份入口:公开注册、邮箱密码登录(Google/GitHub 快捷登录即将上线),全子站单点登录。",
    "liveUrl": "https://account.linzezhang.com",
    "fallbackUrl": "https://account.linzezhang.com/realms/linze/account/",
    "mode": "voyage"
  }
]
